{"type":"FeatureCollection","features":[
{"type":"Feature","properties":{"name":"Gift63297","weight":1},"geometry":{"type":"Point","coordinates":[28.6205,57.8417]},"id":"g63297"},{"type":"Feature","properties":{"name":"Gift35718","weight":1},"geometry":{"type":"Point","coordinates":[28.5438,57.2002]},"id":"g35718"},{"type":"Feature","properties":{"name":"Gift24755","weight":1},"geometry":{"type":"Point","coordinates":[28.4634,51.7275]},"id":"g24755"},{"type":"Feature","properties":{"name":"Gift18538","weight":1},"geometry":{"type":"Point","coordinates":[28.4611,49.0656]},"id":"g18538"},{"type":"Feature","properties":{"name":"Gift51055","weight":1},"geometry":{"type":"Point","coordinates":[28.4658,39.3083]},"id":"g51055"},{"type":"Feature","properties":{"name":"Gift7146","weight":1},"geometry":{"type":"Point","coordinates":[28.2608,30.6336]},"id":"g7146"},{"type":"Feature","properties":{"name":"Gift90358","weight":1},"geometry":{"type":"Point","coordinates":[28.4002,24.845]},"id":"g90358"},{"type":"Feature","properties":{"name":"Gift60875","weight":1},"geometry":{"type":"Point","coordinates":[28.3599,24.2798]},"id":"g60875"},{"type":"Feature","properties":{"name":"Gift49123","weight":1},"geometry":{"type":"Point","coordinates":[28.2067,21.6893]},"id":"g49123"},{"type":"Feature","properties":{"name":"Gift79826","weight":1},"geometry":{"type":"Point","coordinates":[28.16,20.3861]},"id":"g79826"},{"type":"Feature","properties":{"name":"Gift56807","weight":1},"geometry":{"type":"Point","coordinates":[28.1045,10.3573]},"id":"g56807"},{"type":"Feature","properties":{"name":"Gift7326","weight":1.26878},"geometry":{"type":"Point","coordinates":[28.1498,2.43705]},"id":"g7326"},{"type":"Feature","properties":{"name":"Gift41628","weight":1},"geometry":{"type":"Point","coordinates":[28.1755,-1.29167]},"id":"g41628"},{"type":"Feature","properties":{"name":"Gift87865","weight":1},"geometry":{"type":"Point","coordinates":[28.1393,-2.87529]},"id":"g87865"},{"type":"Feature","properties":{"name":"Gift88018","weight":1},"geometry":{"type":"Point","coordinates":[28.1196,-4.51645]},"id":"g88018"},{"type":"Feature","properties":{"name":"Gift19351","weight":1},"geometry":{"type":"Point","coordinates":[28.0837,-5.1951]},"id":"g19351"},{"type":"Feature","properties":{"name":"Gift19663","weight":1},"geometry":{"type":"Point","coordinates":[28.2274,-10.04]},"id":"g19663"},{"type":"Feature","properties":{"name":"Gift2730","weight":2.64804},"geometry":{"type":"Point","coordinates":[28.4574,-14.1307]},"id":"g2730"},{"type":"Feature","properties":{"name":"Gift3955","weight":4.02897},"geometry":{"type":"Point","coordinates":[28.671,-16.3567]},"id":"g3955"},{"type":"Feature","properties":{"name":"Gift62321","weight":1.93107},"geometry":{"type":"Point","coordinates":[28.8739,-19.2376]},"id":"g62321"},{"type":"Feature","properties":{"name":"Gift26336","weight":1},"geometry":{"type":"Point","coordinates":[28.9588,-21.0813]},"id":"g26336"},{"type":"Feature","properties":{"name":"Gift96734","weight":1.27396},"geometry":{"type":"Point","coordinates":[29.2844,-28.0963]},"id":"g96734"},{"type":"Feature","properties":{"name":"Gift93718","weight":44.5337},"geometry":{"type":"Point","coordinates":[29.2673,-31.5502]},"id":"g93718"},{"type":"Feature","properties":{"name":"Gift11003","weight":18.8793},"geometry":{"type":"Point","coordinates":[29.1415,-31.7366]},"id":"g11003"},{"type":"Feature","properties":{"name":"Gift51211","weight":1},"geometry":{"type":"Point","coordinates":[26.1001,-70.3157]},"id":"g51211"},{"type":"Feature","properties":{"name":"Gift2927","weight":1},"geometry":{"type":"Point","coordinates":[26.0062,-70.5658]},"id":"g2927"},{"type":"Feature","properties":{"name":"Gift86350","weight":2.08948},"geometry":{"type":"Point","coordinates":[25.2536,-72.2659]},"id":"g86350"},{"type":"Feature","properties":{"name":"Gift86297","weight":3.38943},"geometry":{"type":"Point","coordinates":[24.3307,-75.0108]},"id":"g86297"},{"type":"Feature","properties":{"name":"Gift94564","weight":1},"geometry":{"type":"Point","coordinates":[24.2322,-76.4846]},"id":"g94564"},{"type":"Feature","properties":{"name":"Gift39141","weight":1},"geometry":{"type":"Point","coordinates":[24.363,-77.4573]},"id":"g39141"},{"type":"Feature","properties":{"name":"Gift56708","weight":12.7562},"geometry":{"type":"Point","coordinates":[24.8496,-77.9153]},"id":"g56708"},{"type":"Feature","properties":{"name":"Gift5832","weight":1},"geometry":{"type":"Point","coordinates":[25.3558,-78.5835]},"id":"g5832"},{"type":"Feature","properties":{"name":"Gift83639","weight":10.8819},"geometry":{"type":"Point","coordinates":[26.4297,-79.2103]},"id":"g83639"},{"type":"Feature","properties":{"name":"Gift54914","weight":8.53582},"geometry":{"type":"Point","coordinates":[26.522,-80.2483]},"id":"g54914"},{"type":"Feature","properties":{"name":"Gift97438","weight":8.63885},"geometry":{"type":"Point","coordinates":[28.9033,-81.1402]},"id":"g97438"},{"type":"Feature","properties":{"name":"Gift32643","weight":20.6152},"geometry":{"type":"Point","coordinates":[29.6676,-81.1901]},"id":"g32643"},{"type":"Feature","properties":{"name":"Gift19485","weight":11.2087},"geometry":{"type":"Point","coordinates":[29.6862,-81.7444]},"id":"g19485"},{"type":"Feature","properties":{"name":"Gift2302","weight":19.3768},"geometry":{"type":"Point","coordinates":[30.1849,-81.9544]},"id":"g2302"},{"type":"Feature","properties":{"name":"Gift61483","weight":23.6348},"geometry":{"type":"Point","coordinates":[28.9525,-82.499]},"id":"g61483"},{"type":"Feature","properties":{"name":"Gift6317","weight":6.21433},"geometry":{"type":"Point","coordinates":[28.9372,-82.9911]},"id":"g6317"},{"type":"Feature","properties":{"name":"Gift84395","weight":17.2622},"geometry":{"type":"Point","coordinates":[28.3981,-83.3839]},"id":"g84395"},{"type":"Feature","properties":{"name":"Gift50930","weight":46.7476},"geometry":{"type":"Point","coordinates":[28.244,-83.8199]},"id":"g50930"},{"type":"Feature","properties":{"name":"Gift50213","weight":29.4278},"geometry":{"type":"Point","coordinates":[28.8826,-84.3207]},"id":"g50213"},{"type":"Feature","properties":{"name":"Gift40083","weight":50},"geometry":{"type":"Point","coordinates":[30.7737,-84.6134]},"id":"g40083"},{"type":"Feature","properties":{"name":"Gift27478","weight":34.7291},"geometry":{"type":"Point","coordinates":[31.283,-84.8432]},"id":"g27478"},{"type":"Feature","properties":{"name":"Gift40221","weight":6.08461},"geometry":{"type":"Point","coordinates":[31.5449,-85.0605]},"id":"g40221"},{"type":"Feature","properties":{"name":"Gift38922","weight":32.5451},"geometry":{"type":"Point","coordinates":[30.7759,-85.5683]},"id":"g38922"},{"type":"Feature","properties":{"name":"Gift82882","weight":40.8466},"geometry":{"type":"Point","coordinates":[29.6818,-85.8598]},"id":"g82882"},{"type":"Feature","properties":{"name":"Gift57769","weight":8.21841},"geometry":{"type":"Point","coordinates":[29.028,-85.9652]},"id":"g57769"},{"type":"Feature","properties":{"name":"Gift41340","weight":26.0436},"geometry":{"type":"Point","coordinates":[29.4451,-86.1614]},"id":"g41340"},{"type":"Feature","properties":{"name":"Gift31607","weight":23.6134},"geometry":{"type":"Point","coordinates":[30.5074,-86.3012]},"id":"g31607"},{"type":"Feature","properties":{"name":"Gift929","weight":15.48},"geometry":{"type":"Point","coordinates":[28.3967,-86.4674]},"id":"g929"},{"type":"Feature","properties":{"name":"Gift5696","weight":24.1315},"geometry":{"type":"Point","coordinates":[29.6519,-86.7068]},"id":"g5696"},{"type":"Feature","properties":{"name":"Gift21341","weight":17.1569},"geometry":{"type":"Point","coordinates":[32.3649,-87.0628]},"id":"g21341"},{"type":"Feature","properties":{"name":"Gift89580","weight":50},"geometry":{"type":"Point","coordinates":[31.7621,-87.2064]},"id":"g89580"},{"type":"Feature","properties":{"name":"Gift11896","weight":24.652},"geometry":{"type":"Point","coordinates":[33.1684,-87.3096]},"id":"g11896"},{"type":"Feature","properties":{"name":"Gift10937","weight":25.4035},"geometry":{"type":"Point","coordinates":[33.8324,-87.3873]},"id":"g10937"},{"type":"Feature","properties":{"name":"Gift80595","weight":13.9365},"geometry":{"type":"Point","coordinates":[34.2202,-87.7547]},"id":"g80595"},{"type":"Feature","properties":{"name":"Gift40849","weight":19.4353},"geometry":{"type":"Point","coordinates":[33.7355,-88.2904]},"id":"g40849"},{"type":"Feature","properties":{"name":"Gift72426","weight":24.027},"geometry":{"type":"Point","coordinates":[35.7097,-88.3385]},"id":"g72426"},{"type":"Feature","properties":{"name":"Gift82064","weight":39.6895},"geometry":{"type":"Point","coordinates":[39.1943,-88.7153]},"id":"g82064"},{"type":"Feature","properties":{"name":"Gift30599","weight":34.2755},"geometry":{"type":"Point","coordinates":[38.3538,-88.7292]},"id":"g30599"},{"type":"Feature","properties":{"name":"Gift60348","weight":10.3431},"geometry":{"type":"Point","coordinates":[39.9561,-88.74]},"id":"g60348"},{"type":"Feature","properties":{"name":"Gift20917","weight":14.7689},"geometry":{"type":"Point","coordinates":[44.7915,-88.8302]},"id":"g20917"},{"type":"Feature","properties":{"name":"Gift25565","weight":28.8529},"geometry":{"type":"Point","coordinates":[36.6713,-89.0586]},"id":"g25565"},{"type":"Feature","properties":{"name":"Gift2810","weight":20.6641},"geometry":{"type":"Point","coordinates":[35.3202,-89.1825]},"id":"g2810"},{"type":"Feature","properties":{"name":"Gift65586","weight":1.62534},"geometry":{"type":"Point","coordinates":[32.7959,-89.2032]},"id":"g65586"},{"type":"Feature","properties":{"name":"Gift70954","weight":13.6577},"geometry":{"type":"Point","coordinates":[26.1855,-89.4277]},"id":"g70954"},{"type":"Feature","properties":{"name":"Gift71760","weight":21.704},"geometry":{"type":"Point","coordinates":[24.0537,-89.4681]},"id":"g71760"},{"type":"Feature","properties":{"name":"Gift38312","weight":22.4978},"geometry":{"type":"Point","coordinates":[19.5338,-89.493]},"id":"g38312"},{"type":"Feature","properties":{"name":"Gift82404","weight":6.54363},"geometry":{"type":"Point","coordinates":[13.7602,-89.4988]},"id":"g82404"},{"type":"Feature","properties":{"name":"Gift13882","weight":15.6651},"geometry":{"type":"Point","coordinates":[4.17707,-89.531]},"id":"g13882"},{"type":"Feature","properties":{"name":"Gift24622","weight":8.85682},"geometry":{"type":"Point","coordinates":[-0.372996,-89.5665]},"id":"g24622"},{"type":"Feature","properties":{"name":"Gift43704","weight":1},"geometry":{"type":"Point","coordinates":[1.74274,-89.6278]},"id":"g43704"},{"type":"Feature","properties":{"name":"Gift46883","weight":1},"geometry":{"type":"Point","coordinates":[-7.54491,-89.5759]},"id":"g46883"},{"type":"Feature","properties":{"name":"Gift51440","weight":1},"geometry":{"type":"Point","coordinates":[2.08315,-89.4882]},"id":"g51440"},{"type":"Feature","properties":{"name":"Gift34523","weight":2.15314},"geometry":{"type":"Point","coordinates":[0.152652,-89.3387]},"id":"g34523"},{"type":"Feature","properties":{"name":"Gift6017","weight":1},"geometry":{"type":"Point","coordinates":[-18.6485,-89.0956]},"id":"g6017"},{"type":"Feature","properties":{"name":"Gift56955","weight":1},"geometry":{"type":"Point","coordinates":[-17.1514,-88.9871]},"id":"g56955"},{"type":"Feature","properties":{"name":"NorthPole"},"geometry":{"type":"Point","coordinates":[0,90]},"id":"np"}
]}