{"type":"FeatureCollection","features":[
{"type":"Feature","properties":{"name":"Gift65463","weight":1},"geometry":{"type":"Point","coordinates":[-50.1442,82.3036]},"id":"g65463"},{"type":"Feature","properties":{"name":"Gift54582","weight":1},"geometry":{"type":"Point","coordinates":[-50.0939,81.2277]},"id":"g54582"},{"type":"Feature","properties":{"name":"Gift51798","weight":1},"geometry":{"type":"Point","coordinates":[-50.2052,78.6178]},"id":"g51798"},{"type":"Feature","properties":{"name":"Gift36798","weight":1},"geometry":{"type":"Point","coordinates":[-50.2781,72.5618]},"id":"g36798"},{"type":"Feature","properties":{"name":"Gift64137","weight":1},"geometry":{"type":"Point","coordinates":[-50.3426,67.4686]},"id":"g64137"},{"type":"Feature","properties":{"name":"Gift43403","weight":6.95458},"geometry":{"type":"Point","coordinates":[-50.3644,65.7477]},"id":"g43403"},{"type":"Feature","properties":{"name":"Gift54701","weight":1.3357},"geometry":{"type":"Point","coordinates":[-50.4002,65.3103]},"id":"g54701"},{"type":"Feature","properties":{"name":"Gift19233","weight":1},"geometry":{"type":"Point","coordinates":[-50.3185,64.8814]},"id":"g19233"},{"type":"Feature","properties":{"name":"Gift98825","weight":1},"geometry":{"type":"Point","coordinates":[-50.538,0.861236]},"id":"g98825"},{"type":"Feature","properties":{"name":"Gift17445","weight":1},"geometry":{"type":"Point","coordinates":[-50.446,-3.61843]},"id":"g17445"},{"type":"Feature","properties":{"name":"Gift16576","weight":8.74294},"geometry":{"type":"Point","coordinates":[-50.3945,-4.16555]},"id":"g16576"},{"type":"Feature","properties":{"name":"Gift61718","weight":1},"geometry":{"type":"Point","coordinates":[-50.3832,-4.77462]},"id":"g61718"},{"type":"Feature","properties":{"name":"Gift54925","weight":3.89005},"geometry":{"type":"Point","coordinates":[-50.3733,-4.79987]},"id":"g54925"},{"type":"Feature","properties":{"name":"Gift20007","weight":12.7105},"geometry":{"type":"Point","coordinates":[-50.4141,-5.21106]},"id":"g20007"},{"type":"Feature","properties":{"name":"Gift12574","weight":24.7224},"geometry":{"type":"Point","coordinates":[-50.4395,-5.60122]},"id":"g12574"},{"type":"Feature","properties":{"name":"Gift53925","weight":4.61061},"geometry":{"type":"Point","coordinates":[-50.4435,-6.33911]},"id":"g53925"},{"type":"Feature","properties":{"name":"Gift96226","weight":1},"geometry":{"type":"Point","coordinates":[-50.4433,-6.70853]},"id":"g96226"},{"type":"Feature","properties":{"name":"Gift63891","weight":7.47604},"geometry":{"type":"Point","coordinates":[-50.5256,-7.46677]},"id":"g63891"},{"type":"Feature","properties":{"name":"Gift75392","weight":21.7397},"geometry":{"type":"Point","coordinates":[-50.4739,-8.37552]},"id":"g75392"},{"type":"Feature","properties":{"name":"Gift86356","weight":8.81895},"geometry":{"type":"Point","coordinates":[-50.4701,-8.92601]},"id":"g86356"},{"type":"Feature","properties":{"name":"Gift12664","weight":4.2771},"geometry":{"type":"Point","coordinates":[-50.4285,-9.79888]},"id":"g12664"},{"type":"Feature","properties":{"name":"Gift18262","weight":35.2968},"geometry":{"type":"Point","coordinates":[-50.4686,-10.1098]},"id":"g18262"},{"type":"Feature","properties":{"name":"Gift30701","weight":2.48207},"geometry":{"type":"Point","coordinates":[-50.3618,-11.6793]},"id":"g30701"},{"type":"Feature","properties":{"name":"Gift22022","weight":11.2528},"geometry":{"type":"Point","coordinates":[-50.2689,-12.6165]},"id":"g22022"},{"type":"Feature","properties":{"name":"Gift48621","weight":18.5352},"geometry":{"type":"Point","coordinates":[-50.3052,-14.9137]},"id":"g48621"},{"type":"Feature","properties":{"name":"Gift99392","weight":16.7466},"geometry":{"type":"Point","coordinates":[-50.263,-15.6316]},"id":"g99392"},{"type":"Feature","properties":{"name":"Gift37214","weight":24.9386},"geometry":{"type":"Point","coordinates":[-50.2493,-15.74]},"id":"g37214"},{"type":"Feature","properties":{"name":"Gift39263","weight":17.4276},"geometry":{"type":"Point","coordinates":[-50.1942,-16.4012]},"id":"g39263"},{"type":"Feature","properties":{"name":"Gift51589","weight":13.4517},"geometry":{"type":"Point","coordinates":[-50.2867,-16.6216]},"id":"g51589"},{"type":"Feature","properties":{"name":"Gift60789","weight":1},"geometry":{"type":"Point","coordinates":[-50.2744,-17.5147]},"id":"g60789"},{"type":"Feature","properties":{"name":"Gift35075","weight":50},"geometry":{"type":"Point","coordinates":[-50.3276,-17.8946]},"id":"g35075"},{"type":"Feature","properties":{"name":"Gift40352","weight":3.74619},"geometry":{"type":"Point","coordinates":[-50.4139,-18.2083]},"id":"g40352"},{"type":"Feature","properties":{"name":"Gift7758","weight":21.9223},"geometry":{"type":"Point","coordinates":[-50.3719,-18.7903]},"id":"g7758"},{"type":"Feature","properties":{"name":"Gift91038","weight":1},"geometry":{"type":"Point","coordinates":[-50.3274,-19.4016]},"id":"g91038"},{"type":"Feature","properties":{"name":"Gift44367","weight":16.3897},"geometry":{"type":"Point","coordinates":[-50.3104,-19.8385]},"id":"g44367"},{"type":"Feature","properties":{"name":"Gift91420","weight":19.3027},"geometry":{"type":"Point","coordinates":[-50.3079,-20.9995]},"id":"g91420"},{"type":"Feature","properties":{"name":"Gift31630","weight":21.1811},"geometry":{"type":"Point","coordinates":[-50.3236,-21.2612]},"id":"g31630"},{"type":"Feature","properties":{"name":"Gift1869","weight":23.9744},"geometry":{"type":"Point","coordinates":[-50.3416,-21.3214]},"id":"g1869"},{"type":"Feature","properties":{"name":"Gift68286","weight":26.9522},"geometry":{"type":"Point","coordinates":[-50.4016,-21.8542]},"id":"g68286"},{"type":"Feature","properties":{"name":"Gift81230","weight":36.3506},"geometry":{"type":"Point","coordinates":[-50.5758,-23.3139]},"id":"g81230"},{"type":"Feature","properties":{"name":"Gift50513","weight":6.988},"geometry":{"type":"Point","coordinates":[-50.6951,-23.5547]},"id":"g50513"},{"type":"Feature","properties":{"name":"Gift1590","weight":31.6079},"geometry":{"type":"Point","coordinates":[-50.6583,-24.1718]},"id":"g1590"},{"type":"Feature","properties":{"name":"Gift22077","weight":25.8846},"geometry":{"type":"Point","coordinates":[-50.6837,-24.1991]},"id":"g22077"},{"type":"Feature","properties":{"name":"Gift76633","weight":50},"geometry":{"type":"Point","coordinates":[-50.5952,-24.6853]},"id":"g76633"},{"type":"Feature","properties":{"name":"Gift34552","weight":5.06774},"geometry":{"type":"Point","coordinates":[-50.4198,-25.4787]},"id":"g34552"},{"type":"Feature","properties":{"name":"Gift95917","weight":24.9324},"geometry":{"type":"Point","coordinates":[-50.229,-27.106]},"id":"g95917"},{"type":"Feature","properties":{"name":"Gift21983","weight":36.1242},"geometry":{"type":"Point","coordinates":[-50.2345,-27.1745]},"id":"g21983"},{"type":"Feature","properties":{"name":"Gift2295","weight":25.3207},"geometry":{"type":"Point","coordinates":[-50.2999,-27.3551]},"id":"g2295"},{"type":"Feature","properties":{"name":"Gift92632","weight":13.4663},"geometry":{"type":"Point","coordinates":[-50.2276,-28.5032]},"id":"g92632"},{"type":"Feature","properties":{"name":"Gift16632","weight":11.5292},"geometry":{"type":"Point","coordinates":[-50.1496,-29.2589]},"id":"g16632"},{"type":"Feature","properties":{"name":"Gift73298","weight":9.34641},"geometry":{"type":"Point","coordinates":[-50.0859,-29.5828]},"id":"g73298"},{"type":"Feature","properties":{"name":"Gift14045","weight":6.66846},"geometry":{"type":"Point","coordinates":[-50.0923,-29.6951]},"id":"g14045"},{"type":"Feature","properties":{"name":"Gift8702","weight":17.3782},"geometry":{"type":"Point","coordinates":[-50.3452,-30.2623]},"id":"g8702"},{"type":"Feature","properties":{"name":"Gift21398","weight":21.7735},"geometry":{"type":"Point","coordinates":[-49.0376,-77.5073]},"id":"g21398"},{"type":"Feature","properties":{"name":"Gift15097","weight":29.0562},"geometry":{"type":"Point","coordinates":[-48.2122,-77.9367]},"id":"g15097"},{"type":"Feature","properties":{"name":"Gift55379","weight":12.4027},"geometry":{"type":"Point","coordinates":[-46.7769,-78.4719]},"id":"g55379"},{"type":"Feature","properties":{"name":"Gift9614","weight":23.1804},"geometry":{"type":"Point","coordinates":[-46.6527,-78.4838]},"id":"g9614"},{"type":"Feature","properties":{"name":"Gift48305","weight":34.1696},"geometry":{"type":"Point","coordinates":[-46.3987,-78.9009]},"id":"g48305"},{"type":"Feature","properties":{"name":"Gift41315","weight":50},"geometry":{"type":"Point","coordinates":[-45.9129,-79.4292]},"id":"g41315"},{"type":"Feature","properties":{"name":"Gift1395","weight":6.43342},"geometry":{"type":"Point","coordinates":[-46.0122,-79.7941]},"id":"g1395"},{"type":"Feature","properties":{"name":"Gift93016","weight":1},"geometry":{"type":"Point","coordinates":[-45.7667,-79.9045]},"id":"g93016"},{"type":"Feature","properties":{"name":"Gift42483","weight":1},"geometry":{"type":"Point","coordinates":[-45.8783,-80.0485]},"id":"g42483"},{"type":"Feature","properties":{"name":"Gift40669","weight":1},"geometry":{"type":"Point","coordinates":[-46.6381,-80.4711]},"id":"g40669"},{"type":"Feature","properties":{"name":"Gift55609","weight":35.3923},"geometry":{"type":"Point","coordinates":[-47.1929,-80.6352]},"id":"g55609"},{"type":"Feature","properties":{"name":"Gift63245","weight":34.1964},"geometry":{"type":"Point","coordinates":[-46.2402,-80.7511]},"id":"g63245"},{"type":"Feature","properties":{"name":"Gift13659","weight":1},"geometry":{"type":"Point","coordinates":[-44.3571,-80.4576]},"id":"g13659"},{"type":"Feature","properties":{"name":"Gift33102","weight":1},"geometry":{"type":"Point","coordinates":[-47.342,-79.6771]},"id":"g33102"},{"type":"Feature","properties":{"name":"Gift82390","weight":1},"geometry":{"type":"Point","coordinates":[-46.5907,-79.3908]},"id":"g82390"},{"type":"Feature","properties":{"name":"Gift89070","weight":1},"geometry":{"type":"Point","coordinates":[-45.1284,-79.2699]},"id":"g89070"},{"type":"Feature","properties":{"name":"Gift6887","weight":1},"geometry":{"type":"Point","coordinates":[-48.2531,-78.9928]},"id":"g6887"},{"type":"Feature","properties":{"name":"Gift30319","weight":1},"geometry":{"type":"Point","coordinates":[-50.9058,-78.4575]},"id":"g30319"},{"type":"Feature","properties":{"name":"NorthPole"},"geometry":{"type":"Point","coordinates":[0,90]},"id":"np"}
]}