{"type":"FeatureCollection","features":[
{"type":"Feature","properties":{"name":"Gift38526","weight":4.59086},"geometry":{"type":"Point","coordinates":[-124.847,72.4958]},"id":"g38526"},{"type":"Feature","properties":{"name":"Gift6599","weight":4.348},"geometry":{"type":"Point","coordinates":[-125.324,69.1928]},"id":"g6599"},{"type":"Feature","properties":{"name":"Gift35719","weight":12.7386},"geometry":{"type":"Point","coordinates":[-125.507,68.5362]},"id":"g35719"},{"type":"Feature","properties":{"name":"Gift43864","weight":18.3016},"geometry":{"type":"Point","coordinates":[-125.429,68.0325]},"id":"g43864"},{"type":"Feature","properties":{"name":"Gift71347","weight":35.2137},"geometry":{"type":"Point","coordinates":[-125.189,66.8796]},"id":"g71347"},{"type":"Feature","properties":{"name":"Gift93686","weight":1},"geometry":{"type":"Point","coordinates":[-125.216,66.1861]},"id":"g93686"},{"type":"Feature","properties":{"name":"Gift20440","weight":26.2146},"geometry":{"type":"Point","coordinates":[-125.141,64.5327]},"id":"g20440"},{"type":"Feature","properties":{"name":"Gift67434","weight":16.3654},"geometry":{"type":"Point","coordinates":[-124.971,63.5007]},"id":"g67434"},{"type":"Feature","properties":{"name":"Gift32987","weight":9.29625},"geometry":{"type":"Point","coordinates":[-124.876,62.9811]},"id":"g32987"},{"type":"Feature","properties":{"name":"Gift38877","weight":1},"geometry":{"type":"Point","coordinates":[-124.755,62.5051]},"id":"g38877"},{"type":"Feature","properties":{"name":"Gift41392","weight":30.2738},"geometry":{"type":"Point","coordinates":[-124.856,60.6215]},"id":"g41392"},{"type":"Feature","properties":{"name":"Gift75356","weight":20.4617},"geometry":{"type":"Point","coordinates":[-125.008,59.4742]},"id":"g75356"},{"type":"Feature","properties":{"name":"Gift39015","weight":3.59421},"geometry":{"type":"Point","coordinates":[-124.934,59.2968]},"id":"g39015"},{"type":"Feature","properties":{"name":"Gift12430","weight":40.4694},"geometry":{"type":"Point","coordinates":[-124.958,58.9498]},"id":"g12430"},{"type":"Feature","properties":{"name":"Gift6987","weight":9.31118},"geometry":{"type":"Point","coordinates":[-124.836,57.5406]},"id":"g6987"},{"type":"Feature","properties":{"name":"Gift37791","weight":31.0661},"geometry":{"type":"Point","coordinates":[-124.303,55.421]},"id":"g37791"},{"type":"Feature","properties":{"name":"Gift47247","weight":44.5112},"geometry":{"type":"Point","coordinates":[-123.993,54.2432]},"id":"g47247"},{"type":"Feature","properties":{"name":"Gift15689","weight":4.28713},"geometry":{"type":"Point","coordinates":[-124.002,53.724]},"id":"g15689"},{"type":"Feature","properties":{"name":"Gift89126","weight":39.2559},"geometry":{"type":"Point","coordinates":[-123.525,51.8054]},"id":"g89126"},{"type":"Feature","properties":{"name":"Gift88981","weight":7.30682},"geometry":{"type":"Point","coordinates":[-123.575,51.6919]},"id":"g88981"},{"type":"Feature","properties":{"name":"Gift20313","weight":10.5597},"geometry":{"type":"Point","coordinates":[-123.635,51.4362]},"id":"g20313"},{"type":"Feature","properties":{"name":"Gift65103","weight":32.0121},"geometry":{"type":"Point","coordinates":[-123.587,51.0095]},"id":"g65103"},{"type":"Feature","properties":{"name":"Gift55344","weight":43.2374},"geometry":{"type":"Point","coordinates":[-123.435,50.8841]},"id":"g55344"},{"type":"Feature","properties":{"name":"Gift38778","weight":25.5045},"geometry":{"type":"Point","coordinates":[-123.464,50.4078]},"id":"g38778"},{"type":"Feature","properties":{"name":"Gift22637","weight":8.87022},"geometry":{"type":"Point","coordinates":[-123.459,50.1039]},"id":"g22637"},{"type":"Feature","properties":{"name":"Gift55748","weight":1},"geometry":{"type":"Point","coordinates":[-123.449,49.8215]},"id":"g55748"},{"type":"Feature","properties":{"name":"Gift24982","weight":12.1103},"geometry":{"type":"Point","coordinates":[-123.504,48.8052]},"id":"g24982"},{"type":"Feature","properties":{"name":"Gift16496","weight":14.3621},"geometry":{"type":"Point","coordinates":[-123.301,47.7854]},"id":"g16496"},{"type":"Feature","properties":{"name":"Gift22397","weight":3.74842},"geometry":{"type":"Point","coordinates":[-123.371,47.1847]},"id":"g22397"},{"type":"Feature","properties":{"name":"Gift7913","weight":29.1072},"geometry":{"type":"Point","coordinates":[-123.337,46.9482]},"id":"g7913"},{"type":"Feature","properties":{"name":"Gift78734","weight":24.9229},"geometry":{"type":"Point","coordinates":[-123.257,46.0829]},"id":"g78734"},{"type":"Feature","properties":{"name":"Gift93038","weight":1},"geometry":{"type":"Point","coordinates":[-123.172,45.3714]},"id":"g93038"},{"type":"Feature","properties":{"name":"Gift18790","weight":45.9384},"geometry":{"type":"Point","coordinates":[-123.266,44.3706]},"id":"g18790"},{"type":"Feature","properties":{"name":"Gift41357","weight":1},"geometry":{"type":"Point","coordinates":[-123.251,43.6205]},"id":"g41357"},{"type":"Feature","properties":{"name":"Gift25336","weight":50},"geometry":{"type":"Point","coordinates":[-123.124,43.3476]},"id":"g25336"},{"type":"Feature","properties":{"name":"Gift56621","weight":1},"geometry":{"type":"Point","coordinates":[-123.405,42.7252]},"id":"g56621"},{"type":"Feature","properties":{"name":"Gift23839","weight":5.05917},"geometry":{"type":"Point","coordinates":[-123.374,42.3863]},"id":"g23839"},{"type":"Feature","properties":{"name":"Gift63827","weight":50},"geometry":{"type":"Point","coordinates":[-123.224,42.2414]},"id":"g63827"},{"type":"Feature","properties":{"name":"Gift64240","weight":14.2731},"geometry":{"type":"Point","coordinates":[-123.177,41.5304]},"id":"g64240"},{"type":"Feature","properties":{"name":"Gift9594","weight":1},"geometry":{"type":"Point","coordinates":[-123.118,41.2607]},"id":"g9594"},{"type":"Feature","properties":{"name":"Gift56641","weight":15.5894},"geometry":{"type":"Point","coordinates":[-123.053,40.8261]},"id":"g56641"},{"type":"Feature","properties":{"name":"Gift18644","weight":19.8484},"geometry":{"type":"Point","coordinates":[-123.021,40.1714]},"id":"g18644"},{"type":"Feature","properties":{"name":"Gift55281","weight":29.0157},"geometry":{"type":"Point","coordinates":[-122.895,40.0146]},"id":"g55281"},{"type":"Feature","properties":{"name":"Gift32622","weight":50},"geometry":{"type":"Point","coordinates":[-122.742,39.6624]},"id":"g32622"},{"type":"Feature","properties":{"name":"Gift54163","weight":14.7453},"geometry":{"type":"Point","coordinates":[-122.714,39.5392]},"id":"g54163"},{"type":"Feature","properties":{"name":"Gift58031","weight":13.5612},"geometry":{"type":"Point","coordinates":[-122.318,39.0321]},"id":"g58031"},{"type":"Feature","properties":{"name":"Gift16457","weight":4.21335},"geometry":{"type":"Point","coordinates":[-122.639,38.807]},"id":"g16457"},{"type":"Feature","properties":{"name":"Gift61337","weight":16.9144},"geometry":{"type":"Point","coordinates":[-122.609,38.6511]},"id":"g61337"},{"type":"Feature","properties":{"name":"Gift38650","weight":19.9424},"geometry":{"type":"Point","coordinates":[-122.739,38.3602]},"id":"g38650"},{"type":"Feature","properties":{"name":"Gift27719","weight":37.62},"geometry":{"type":"Point","coordinates":[-122.555,38.1543]},"id":"g27719"},{"type":"Feature","properties":{"name":"Gift34350","weight":24.0576},"geometry":{"type":"Point","coordinates":[-122.356,38.0027]},"id":"g34350"},{"type":"Feature","properties":{"name":"Gift37623","weight":13.2798},"geometry":{"type":"Point","coordinates":[-122.711,37.9882]},"id":"g37623"},{"type":"Feature","properties":{"name":"Gift49334","weight":1},"geometry":{"type":"Point","coordinates":[-122.924,38.2216]},"id":"g49334"},{"type":"Feature","properties":{"name":"Gift33076","weight":1},"geometry":{"type":"Point","coordinates":[-122.497,38.331]},"id":"g33076"},{"type":"Feature","properties":{"name":"Gift26779","weight":1},"geometry":{"type":"Point","coordinates":[-122.433,38.8649]},"id":"g26779"},{"type":"Feature","properties":{"name":"Gift59225","weight":1},"geometry":{"type":"Point","coordinates":[-122.049,39.2921]},"id":"g59225"},{"type":"Feature","properties":{"name":"NorthPole"},"geometry":{"type":"Point","coordinates":[0,90]},"id":"np"}
]}