{"type":"FeatureCollection","features":[
{"type":"Feature","properties":{"name":"Gift48729","weight":50},"geometry":{"type":"Point","coordinates":[143.291,71.635]},"id":"g48729"},{"type":"Feature","properties":{"name":"Gift55746","weight":38.8624},"geometry":{"type":"Point","coordinates":[143.223,70.7032]},"id":"g55746"},{"type":"Feature","properties":{"name":"Gift12063","weight":4.70584},"geometry":{"type":"Point","coordinates":[143.287,68.434]},"id":"g12063"},{"type":"Feature","properties":{"name":"Gift87972","weight":1},"geometry":{"type":"Point","coordinates":[143.142,67.5099]},"id":"g87972"},{"type":"Feature","properties":{"name":"Gift55756","weight":32.2786},"geometry":{"type":"Point","coordinates":[143.161,67.0751]},"id":"g55756"},{"type":"Feature","properties":{"name":"Gift532","weight":27.4023},"geometry":{"type":"Point","coordinates":[143.177,66.0229]},"id":"g532"},{"type":"Feature","properties":{"name":"Gift77316","weight":26.1954},"geometry":{"type":"Point","coordinates":[143.064,65.2783]},"id":"g77316"},{"type":"Feature","properties":{"name":"Gift78826","weight":6.20941},"geometry":{"type":"Point","coordinates":[143.01,63.6291]},"id":"g78826"},{"type":"Feature","properties":{"name":"Gift96006","weight":23.155},"geometry":{"type":"Point","coordinates":[142.9,62.4567]},"id":"g96006"},{"type":"Feature","properties":{"name":"Gift35710","weight":22.6705},"geometry":{"type":"Point","coordinates":[142.832,62.2435]},"id":"g35710"},{"type":"Feature","properties":{"name":"Gift23068","weight":38.5347},"geometry":{"type":"Point","coordinates":[142.806,61.7383]},"id":"g23068"},{"type":"Feature","properties":{"name":"Gift38984","weight":5.50225},"geometry":{"type":"Point","coordinates":[142.835,61.0633]},"id":"g38984"},{"type":"Feature","properties":{"name":"Gift74210","weight":16.8055},"geometry":{"type":"Point","coordinates":[142.904,59.6321]},"id":"g74210"},{"type":"Feature","properties":{"name":"Gift17906","weight":27.5972},"geometry":{"type":"Point","coordinates":[142.925,59.3606]},"id":"g17906"},{"type":"Feature","properties":{"name":"Gift68204","weight":25.4517},"geometry":{"type":"Point","coordinates":[142.795,54.2905]},"id":"g68204"},{"type":"Feature","properties":{"name":"Gift31583","weight":24.2376},"geometry":{"type":"Point","coordinates":[142.826,54.0241]},"id":"g31583"},{"type":"Feature","properties":{"name":"Gift70140","weight":41.9854},"geometry":{"type":"Point","coordinates":[142.734,52.8655]},"id":"g70140"},{"type":"Feature","properties":{"name":"Gift30573","weight":13.0598},"geometry":{"type":"Point","coordinates":[142.812,52.2969]},"id":"g30573"},{"type":"Feature","properties":{"name":"Gift4305","weight":16.0656},"geometry":{"type":"Point","coordinates":[142.803,50.8718]},"id":"g4305"},{"type":"Feature","properties":{"name":"Gift12532","weight":7.08492},"geometry":{"type":"Point","coordinates":[142.955,49.2091]},"id":"g12532"},{"type":"Feature","properties":{"name":"Gift53083","weight":2.07347},"geometry":{"type":"Point","coordinates":[142.955,44.5237]},"id":"g53083"},{"type":"Feature","properties":{"name":"Gift35665","weight":1},"geometry":{"type":"Point","coordinates":[142.952,43.9331]},"id":"g35665"},{"type":"Feature","properties":{"name":"Gift7512","weight":37.5352},"geometry":{"type":"Point","coordinates":[143.002,42.7721]},"id":"g7512"},{"type":"Feature","properties":{"name":"Gift24166","weight":37.5108},"geometry":{"type":"Point","coordinates":[142.933,42.3379]},"id":"g24166"},{"type":"Feature","properties":{"name":"Gift52492","weight":1},"geometry":{"type":"Point","coordinates":[143.435,-3.77886]},"id":"g52492"},{"type":"Feature","properties":{"name":"Gift96929","weight":38.455},"geometry":{"type":"Point","coordinates":[143.447,-4.38075]},"id":"g96929"},{"type":"Feature","properties":{"name":"Gift23426","weight":47.594},"geometry":{"type":"Point","coordinates":[143.436,-4.65266]},"id":"g23426"},{"type":"Feature","properties":{"name":"Gift47404","weight":22.7847},"geometry":{"type":"Point","coordinates":[143.312,-6.01687]},"id":"g47404"},{"type":"Feature","properties":{"name":"Gift73841","weight":1},"geometry":{"type":"Point","coordinates":[143.373,-6.16252]},"id":"g73841"},{"type":"Feature","properties":{"name":"Gift68195","weight":17.956},"geometry":{"type":"Point","coordinates":[143.28,-6.71536]},"id":"g68195"},{"type":"Feature","properties":{"name":"Gift20267","weight":1},"geometry":{"type":"Point","coordinates":[143.219,-7.12654]},"id":"g20267"},{"type":"Feature","properties":{"name":"Gift59220","weight":3.83163},"geometry":{"type":"Point","coordinates":[143.191,-7.32021]},"id":"g59220"},{"type":"Feature","properties":{"name":"Gift53930","weight":46.5635},"geometry":{"type":"Point","coordinates":[143.303,-7.75695]},"id":"g53930"},{"type":"Feature","properties":{"name":"Gift42370","weight":10.4993},"geometry":{"type":"Point","coordinates":[143.443,-7.89046]},"id":"g42370"},{"type":"Feature","properties":{"name":"Gift21540","weight":6.54547},"geometry":{"type":"Point","coordinates":[143.38,-8.05078]},"id":"g21540"},{"type":"Feature","properties":{"name":"Gift95630","weight":1},"geometry":{"type":"Point","coordinates":[143.467,-8.41806]},"id":"g95630"},{"type":"Feature","properties":{"name":"Gift62580","weight":11.2767},"geometry":{"type":"Point","coordinates":[144.592,-14.6381]},"id":"g62580"},{"type":"Feature","properties":{"name":"Gift42239","weight":50},"geometry":{"type":"Point","coordinates":[144.893,-15.1446]},"id":"g42239"},{"type":"Feature","properties":{"name":"Gift80245","weight":11.0069},"geometry":{"type":"Point","coordinates":[144.995,-15.8442]},"id":"g80245"},{"type":"Feature","properties":{"name":"Gift77799","weight":11.6753},"geometry":{"type":"Point","coordinates":[145.079,-17.3104]},"id":"g77799"},{"type":"Feature","properties":{"name":"Gift48913","weight":27.5178},"geometry":{"type":"Point","coordinates":[145.155,-17.8081]},"id":"g48913"},{"type":"Feature","properties":{"name":"Gift27726","weight":3.13227},"geometry":{"type":"Point","coordinates":[145.392,-18.0526]},"id":"g27726"},{"type":"Feature","properties":{"name":"Gift46655","weight":24.6367},"geometry":{"type":"Point","coordinates":[145.437,-18.2872]},"id":"g46655"},{"type":"Feature","properties":{"name":"Gift20477","weight":1},"geometry":{"type":"Point","coordinates":[145.423,-18.3339]},"id":"g20477"},{"type":"Feature","properties":{"name":"Gift44467","weight":1.40496},"geometry":{"type":"Point","coordinates":[145.503,-18.4441]},"id":"g44467"},{"type":"Feature","properties":{"name":"Gift57345","weight":6.22963},"geometry":{"type":"Point","coordinates":[145.471,-18.5922]},"id":"g57345"},{"type":"Feature","properties":{"name":"Gift16790","weight":1},"geometry":{"type":"Point","coordinates":[145.84,-19.464]},"id":"g16790"},{"type":"Feature","properties":{"name":"Gift10449","weight":1},"geometry":{"type":"Point","coordinates":[145.901,-19.7293]},"id":"g10449"},{"type":"Feature","properties":{"name":"Gift36825","weight":1},"geometry":{"type":"Point","coordinates":[145.973,-20.0453]},"id":"g36825"},{"type":"Feature","properties":{"name":"Gift88947","weight":1},"geometry":{"type":"Point","coordinates":[146.594,-20.3976]},"id":"g88947"},{"type":"Feature","properties":{"name":"Gift87621","weight":1},"geometry":{"type":"Point","coordinates":[146.69,-20.6167]},"id":"g87621"},{"type":"Feature","properties":{"name":"Gift37692","weight":1},"geometry":{"type":"Point","coordinates":[146.844,-21.0302]},"id":"g37692"},{"type":"Feature","properties":{"name":"Gift47941","weight":5.51158},"geometry":{"type":"Point","coordinates":[147.019,-21.7647]},"id":"g47941"},{"type":"Feature","properties":{"name":"Gift46048","weight":1},"geometry":{"type":"Point","coordinates":[146.708,-23.1275]},"id":"g46048"},{"type":"Feature","properties":{"name":"Gift43890","weight":37.0315},"geometry":{"type":"Point","coordinates":[146.858,-23.8846]},"id":"g43890"},{"type":"Feature","properties":{"name":"Gift25561","weight":29.6981},"geometry":{"type":"Point","coordinates":[147.148,-24.0119]},"id":"g25561"},{"type":"Feature","properties":{"name":"Gift69414","weight":9.06936},"geometry":{"type":"Point","coordinates":[147.244,-23.9744]},"id":"g69414"},{"type":"Feature","properties":{"name":"Gift23900","weight":1},"geometry":{"type":"Point","coordinates":[147.529,-23.8209]},"id":"g23900"},{"type":"Feature","properties":{"name":"Gift38812","weight":14.7692},"geometry":{"type":"Point","coordinates":[147.699,-24.0462]},"id":"g38812"},{"type":"Feature","properties":{"name":"Gift763","weight":1},"geometry":{"type":"Point","coordinates":[147.592,-24.6046]},"id":"g763"},{"type":"Feature","properties":{"name":"Gift52075","weight":1},"geometry":{"type":"Point","coordinates":[148.13,-24.7815]},"id":"g52075"},{"type":"Feature","properties":{"name":"Gift86805","weight":1},"geometry":{"type":"Point","coordinates":[148.089,-24.5556]},"id":"g86805"},{"type":"Feature","properties":{"name":"Gift59962","weight":1},"geometry":{"type":"Point","coordinates":[148.165,-24.4443]},"id":"g59962"},{"type":"Feature","properties":{"name":"Gift33181","weight":1},"geometry":{"type":"Point","coordinates":[149.104,-23.9217]},"id":"g33181"},{"type":"Feature","properties":{"name":"Gift614","weight":1},"geometry":{"type":"Point","coordinates":[148.776,-22.0422]},"id":"g614"},{"type":"Feature","properties":{"name":"Gift31050","weight":1},"geometry":{"type":"Point","coordinates":[149.306,-21.6405]},"id":"g31050"},{"type":"Feature","properties":{"name":"Gift87207","weight":1},"geometry":{"type":"Point","coordinates":[149.14,-21.4843]},"id":"g87207"},{"type":"Feature","properties":{"name":"Gift24187","weight":1},"geometry":{"type":"Point","coordinates":[148.925,-21.5102]},"id":"g24187"},{"type":"Feature","properties":{"name":"Gift20181","weight":4.43545},"geometry":{"type":"Point","coordinates":[148.829,-21.431]},"id":"g20181"},{"type":"Feature","properties":{"name":"Gift82979","weight":1},"geometry":{"type":"Point","coordinates":[147.684,-20.1475]},"id":"g82979"},{"type":"Feature","properties":{"name":"NorthPole"},"geometry":{"type":"Point","coordinates":[0,90]},"id":"np"}
]}